psyshort/__init__.py
psyshort/psyshort.py
psyshort-0.1.6.dist-info/METADATA
psyshort-0.1.6.dist-info/RECORD
psyshort-0.1.6.dist-info/WHEEL
psyshort-0.1.6.dist-info/top_level.txt
