Metadata-Version: 2.1
Name: psyshort
Version: 0.1.6
Summary: Making psycopg2 a little simpler to use.
Home-page: https://github.com/Quit3Simpl3/psyshort
Author: Quit3Simpl3
License: UNKNOWN
Platform: UNKNOWN
Classifier: Programming Language :: Python :: 3
